hatch_flex.py
hatch_flex-0.0.2.dist-info/METADATA
hatch_flex-0.0.2.dist-info/WHEEL
hatch_flex-0.0.2.dist-info/entry_points.txt
hatch_flex-0.0.2.dist-info/licenses/LICENSE.txt
hatch_flex-0.0.2.dist-info/RECORD
