Metadata-Version: 2.1
Name: hatch-flex
Version: 0.0.2
Summary: Hatch plugin to customize build dependencies
Project-URL: homepage, https://github.com/furechan/hatch-flex
Author-email: furechan <furechan@xsmail.com>
License-File: LICENSE.txt
Keywords: build,editable,hatch,packaging,plugin
Classifier: License :: OSI Approved :: MIT License
Classifier: Operating System :: OS Independent
Classifier: Programming Language :: Python :: 3
Requires-Python: >=3.9
Requires-Dist: hatchling
